wdog.py
wdog-1.0.1.dist-info/LICENCE.txt
wdog-1.0.1.dist-info/METADATA
wdog-1.0.1.dist-info/WHEEL
wdog-1.0.1.dist-info/top_level.txt
wdog-1.0.1.dist-info/RECORD
