Metadata-Version: 2.1
Name: wdog
Version: 1.0.1
Summary: A File System Watch dog
Home-page: UNKNOWN
License: UNKNOWN
Platform: UNKNOWN
Classifier: Programming Language :: Python :: 3
Classifier: Programming Language :: Python :: 3.6
Classifier: Programming Language :: Python :: 3.7
Classifier: Operating System :: OS Independent
Requires-Dist: watchdog (>=0.8.3)
